h2o_engine_manager/__init__.py
h2o_engine_manager/_version.py
h2o_engine_manager/clients/__init__.py
h2o_engine_manager/clients/connection_config.py
h2o_engine_manager/clients/exception.py
h2o_engine_manager/clients/login.py
h2o_engine_manager/clients/auth/__init__.py
h2o_engine_manager/clients/auth/token_api_client.py
h2o_engine_manager/clients/base/__init__.py
h2o_engine_manager/clients/base/image_pull_policy.py
h2o_engine_manager/clients/constraint/__init__.py
h2o_engine_manager/clients/constraint/profile_constraint_duration.py
h2o_engine_manager/clients/constraint/profile_constraint_numeric.py
h2o_engine_manager/clients/convert/__init__.py
h2o_engine_manager/clients/convert/duration_convertor.py
h2o_engine_manager/clients/convert/quantity_convertor.py
h2o_engine_manager/clients/dai_engine/__init__.py
h2o_engine_manager/clients/dai_engine/client_info.py
h2o_engine_manager/clients/dai_engine/dai_engine.py
h2o_engine_manager/clients/dai_engine/dai_engine_client.py
h2o_engine_manager/clients/dai_engine/dai_engine_page.py
h2o_engine_manager/clients/dai_engine/dai_engine_state.py
h2o_engine_manager/clients/dai_engine/dai_engine_version_info.py
h2o_engine_manager/clients/dai_engine/expression.py
h2o_engine_manager/clients/dai_engine/profile_info.py
h2o_engine_manager/clients/dai_engine_profile/__init__.py
h2o_engine_manager/clients/dai_engine_profile/client.py
h2o_engine_manager/clients/dai_engine_profile/config_editability.py
h2o_engine_manager/clients/dai_engine_profile/dai_engine_profile.py
h2o_engine_manager/clients/dai_engine_profile/dai_engine_profile_config.py
h2o_engine_manager/clients/dai_engine_profile/page.py
h2o_engine_manager/clients/dai_engine_version/__init__.py
h2o_engine_manager/clients/dai_engine_version/client.py
h2o_engine_manager/clients/dai_engine_version/dai_engine_version_config.py
h2o_engine_manager/clients/dai_engine_version/page.py
h2o_engine_manager/clients/dai_engine_version/version.py
h2o_engine_manager/clients/dai_license/__init__.py
h2o_engine_manager-1.4.0.dist-info/METADATA
h2o_engine_manager-1.4.0.dist-info/WHEEL
h2o_engine_manager-1.4.0.dist-info/RECORD
