Metadata-Version: 2.4
Name: h2o-engine-manager
Version: 1.4.0
Summary: Python client for H2O Engine Manager
Project-URL: Documentation, https://docs.h2o.ai/ai-engine-manager/py/initialization
Author-email: "H2O.ai" <support@h2o.ai>
Requires-Python: >=3.8
Requires-Dist: driverlessai>=1.10.0
Requires-Dist: h2o-authn>=1.0.0
Requires-Dist: h2o-client>=3.38.0.2
Requires-Dist: h2o-cloud-discovery>=2.1.0
Requires-Dist: python-dateutil>=2.8.2
Requires-Dist: requests>=2.26.0
Requires-Dist: toml>=0.10.2
